<Alloy>
    <Window id="survey">
        <View class="header">
            <Require src="components/closeButton" id="closeButton" onClick="onClickCloseButton" />
            <Label id="headerTitle" class="headerTitle" />

            <View class="timerContainer">
                <Label class="timer" id="surveyTimer" />
                <Label class="startTime" id="surveyStartTime" />
            </View>
        </View>

        <View id="startSurveyContainer">
            <Require src="components/button" id="startSurvey" onClick="doClickStartSurvey" />
        </View>
        <View id="sightingContainer">
            <Require src="components/button" id="addSighting" onClick="doClickAddSighting" />
        </View>
        <View id="finishSurveyContainer">
            <Require src="components/button" id="finishSurvey" onClick="doClickFinishSurvey" />
        </View>

        <ScrollView class="content">
            <View id="preSurvey">
                <Label class="preSurveyMessage" />
            </View>
        </ScrollView>
    </Window>
</Alloy>
